django_medilab_ds/__init__.py
django_medilab_ds/admin.py
django_medilab_ds/apps.py
django_medilab_ds/forms.py
django_medilab_ds/models.py
django_medilab_ds/tests.py
django_medilab_ds/urls.py
django_medilab_ds/views.py
django_medilab_ds/migrations/__init__.py
django_medilab_ds/static/medilabds/css/style.css
django_medilab_ds/static/medilabds/js/main.js
django_medilab_ds/static/medilabds/scss/_footer.scss
django_medilab_ds/static/medilabds/scss/_general.scss
django_medilab_ds/static/medilabds/scss/_header.scss
django_medilab_ds/static/medilabds/scss/_hero.scss
django_medilab_ds/static/medilabds/scss/_nav.scss
django_medilab_ds/static/medilabds/scss/_sections.scss
django_medilab_ds/static/medilabds/scss/_variables.scss
django_medilab_ds/static/medilabds/scss/style.scss
django_medilab_ds/static/medilabds/vendor/animate.css/animate.compat.css
django_medilab_ds/static/medilabds/vendor/animate.css/animate.css
django_medilab_ds/static/medilabds/vendor/animate.css/animate.min.css
django_medilab_ds/static/medilabds/vendor/bootstrap/css/bootstrap-grid.css
django_medilab_ds/static/medilabds/vendor/bootstrap/css/bootstrap-grid.css.map
django_medilab_ds/static/medilabds/vendor/bootstrap/css/bootstrap-grid.min.css
django_medilab_ds/static/medilabds/vendor/bootstrap/css/bootstrap-grid.min.css.map
django_medilab_ds/static/medilabds/vendor/bootstrap/css/bootstrap-grid.rtl.css
django_medilab_ds/static/medilabds/vendor/bootstrap/css/bootstrap-grid.rtl.css.map
django_medilab_ds/static/medilabds/vendor/bootstrap/css/bootstrap-grid.rtl.min.css
django_medilab_ds/static/medilabds/vendor/bootstrap/css/bootstrap-grid.rtl.min.css.map
django_medilab_ds/static/medilabds/vendor/bootstrap/css/bootstrap-reboot.css
django_medilab_ds/static/medilabds/vendor/bootstrap/css/bootstrap-reboot.css.map
django_medilab_ds/static/medilabds/vendor/bootstrap/css/bootstrap-reboot.min.css
django_medilab_ds/static/medilabds/vendor/bootstrap/css/bootstrap-reboot.min.css.map
django_medilab_ds-3.1.0.dist-info/LICENSE
django_medilab_ds-3.1.0.dist-info/WHEEL
django_medilab_ds-3.1.0.dist-info/METADATA
django_medilab_ds-3.1.0.dist-info/RECORD
